setec/__init__.py
setec/version.py
setec-0.0.2.dist-info/METADATA
setec-0.0.2.dist-info/RECORD
setec-0.0.2.dist-info/WHEEL
setec-0.0.2.dist-info/top_level.txt
